{"cameraMode":{"drawMode":0,"name":"Shaded","section":"Shading Mode"},"sceneLighting":true,"audioPlay":false,"sceneViewState":{"showFog":true,"showMaterialUpdate":false,"showSkybox":true,"showFlares":true,"showImageEffects":true,"showParticleSystems":true},"in2DMode":false,"pivot":{"x":13.614640235900879,"y":2.567664861679077,"z":-3.836012840270996},"rotation":{"x":0.062136437743902209,"y":0.46989670395851138,"z":-0.033182770013809207,"w":0.8799073696136475},"size":4.613234519958496,"orthographic":false}